jobutils_pdiegel/__init__.py
jobutils_pdiegel/ascii_file.py
jobutils_pdiegel/cogo_file.py
jobutils_pdiegel/constants.py
jobutils_pdiegel/destination_path_generator.py
jobutils_pdiegel/job_number_parser.py
jobutils_pdiegel-0.4.dist-info/METADATA
jobutils_pdiegel-0.4.dist-info/WHEEL
jobutils_pdiegel-0.4.dist-info/top_level.txt
jobutils_pdiegel-0.4.dist-info/RECORD
