Metadata-Version: 2.1
Name: jobutils_pdiegel
Version: 0.4
Requires-Dist: python-dotenv
